gitleague_client/__init__.py
gitleague_client/api_client.py
gitleague_client/cli.py
gitleague_client/config.py
gitleague_client/exceptions.py
gitleague_client/git_scanner.py
gitleague_client/sync.py
gitleague_client-0.1.0.dist-info/METADATA
gitleague_client-0.1.0.dist-info/WHEEL
gitleague_client-0.1.0.dist-info/entry_points.txt
gitleague_client-0.1.0.dist-info/top_level.txt
gitleague_client-0.1.0.dist-info/RECORD
