Metadata-Version: 2.4
Name: gitleague-client
Version: 0.1.0
Summary: Push commits from local repositories to GitLeague
Author-email: GitLeague Team <hello@thegitleague.com>
License: MIT
Keywords: git,league,gamification
Classifier: Development Status :: 3 - Alpha
Classifier: Intended Audience :: Developers
Classifier: License :: OSI Approved :: MIT License
Classifier: Programming Language :: Python :: 3
Classifier: Programming Language :: Python :: 3.10
Classifier: Programming Language :: Python :: 3.11
Classifier: Programming Language :: Python :: 3.12
Classifier: Programming Language :: Python :: 3.13
Classifier: Topic :: Software Development :: Version Control :: Git
Requires-Python: >=3.10
Requires-Dist: click>=8.1.0
Requires-Dist: GitPython>=3.1.40
Requires-Dist: httpx>=0.26.0
Requires-Dist: pyyaml>=6.0
Requires-Dist: pydantic>=2.5.0
Requires-Dist: rich>=13.7.0
Provides-Extra: dev
Requires-Dist: pytest>=7.0; extra == "dev"
Requires-Dist: pytest-cov>=4.0; extra == "dev"
Requires-Dist: black>=23.0; extra == "dev"
Requires-Dist: ruff>=0.1.0; extra == "dev"
Requires-Dist: mypy>=1.0; extra == "dev"
